neuflow/__init__.py
neuflow/epinf.py
neuflow/ngp.py
neuflow/datasets/__init__.py
neuflow/datasets/api.py
neuflow/datasets/image_mask.py
neuflow/datasets/nerf_synthetic.py
neuflow/datasets/pi_neuflow.py
neuflow/fluids/__init__.py
neuflow/fluids/advection.py
neuflow/models/__init__.py
neuflow/models/api.py
neuflow/models/epinf.py
neuflow/models/ngp.py
neuflow/plugins/__init__.py
neuflow/plugins/api.py
neuflow/plugins/extra_loss.py
neuflow/plugins/train_sapce.py
neuflow/renderers/__init__.py
neuflow/renderers/api.py
neuflow/renderers/epinf.py
neuflow/renderers/ngp.py
neuflow-0.1.4.dist-info/licenses/LICENSE
neuflow-0.1.4.dist-info/METADATA
neuflow-0.1.4.dist-info/WHEEL
neuflow-0.1.4.dist-info/top_level.txt
neuflow-0.1.4.dist-info/RECORD
