Metadata-Version: 2.4
Name: neuflow
Version: 0.1.4
Summary: The pytorch implementation of the paper 'EPINF: Efficient Physics Informed Fluid Flow Reconstruction With Spatial and Temporal Priors'
Author-email: Xayah Hina <ycxiang14sep@gmail.com>
License-Expression: MPL-2.0
Project-URL: Homepage, https://github.com/IME-lab-Hokudai/EPINF-NeuFlow
Classifier: Programming Language :: Python :: 3
Classifier: Operating System :: OS Independent
Requires-Python: >=3.11
License-File: LICENSE
Requires-Dist: lightning
Requires-Dist: lightning[extra]
Requires-Dist: dearpygui
Requires-Dist: tyro
Requires-Dist: matplotlib
Requires-Dist: av
Requires-Dist: huggingface_hub
Requires-Dist: opencv-python
Requires-Dist: phiflow
Dynamic: license-file
